CONTRIBUTING.rst
HISTORY.rst
LICENSE
MANIFEST.in
README.rst
setup.cfg
setup.py
docs/Makefile
docs/conf.py
docs/contributing.rst
docs/history.rst
docs/index.rst
docs/installation.rst
docs/make.bat
docs/readme.rst
docs/usage.rst
raspberry/__init__.py
raspberry/raspberry.py
raspberry.egg-info/PKG-INFO
raspberry.egg-info/SOURCES.txt
raspberry.egg-info/dependency_links.txt
raspberry.egg-info/not-zip-safe
raspberry.egg-info/top_level.txt
tests/__init__.py
tests/test_raspberry.py