Metadata-Version: 1.1
Name: raspberry
Version: 0.0.1
Summary: food
Home-page: https://github.com/j1c/raspberry
Author: Jaewon Chung
Author-email: j1c@jhu.edu
License: Apache Software License 2.0
Keywords: raspberry
Platform: UNKNOWN
Classifier: Development Status :: 2 - Pre-Alpha
Classifier: Intended Audience :: Developers
Classifier: License :: OSI Approved :: Apache Software License
Classifier: Natural Language :: English
Classifier: Programming Language :: Python :: 2
Classifier: Programming Language :: Python :: 2.7
Classifier: Programming Language :: Python :: 3
Classifier: Programming Language :: Python :: 3.4
Classifier: Programming Language :: Python :: 3.5
Classifier: Programming Language :: Python :: 3.6
Classifier: Programming Language :: Python :: 3.7
